formed/__init__.py
formed/__main__.py
formed/commands/__init__.py
formed/commands/subcommand.py
formed/commands/workflow.py
formed/common/__init__.py
formed/common/astutils.py
formed/common/attributeutils.py
formed/common/base58.py
formed/common/ctxutils.py
formed/common/dag.py
formed/common/dataset.py
formed/common/git.py
formed/common/hashutils.py
formed/common/iterutils.py
formed/common/jax.py
formed/common/jsonnet.py
formed/common/logutils.py
formed/common/nlputils.py
formed/common/pkgutils.py
formed/common/rich.py
formed/common/singleton.py
formed/common/typeutils.py
formed/constants.py
formed/integrations/__init__.py
formed/integrations/datasets/__init__.py
formed/integrations/datasets/types.py
formed/integrations/datasets/workflow.py
formed/integrations/flax/__init__.py
formed/integrations/flax/distributors.py
formed/integrations/flax/model.py
formed/integrations/flax/modules/__init__.py
formed/integrations/flax/modules/embedders.py
formed/integrations/flax/modules/encoders.py
formed/integrations/flax/modules/feedforward.py
formed/integrations/flax/modules/losses.py
formed/integrations/flax/modules/samplers.py
formed/integrations/flax/modules/vectorizers.py
formed/integrations/flax/modules/weighters.py
formed/integrations/flax/random.py
formed/integrations/flax/training/__init__.py
formed/integrations/flax/training/callbacks.py
formed/integrations/flax/training/engine.py
formed/integrations/flax/training/exceptions.py
formed/integrations/flax/training/state.py
formed/integrations/flax/training/trainer.py
formed/integrations/flax/types.py
formed/integrations/flax/utils.py
formed/integrations/flax/workflow.py
formed/integrations/ml/__init__.py
formed/integrations/ml/dataloader.py
formed/integrations/ml/metrics.py
formed/integrations/ml/transforms/__init__.py
formed/integrations/ml/transforms/base.py
formed/integrations/ml/transforms/basic.py
formed/integrations/ml/transforms/nlp.py
formed/integrations/ml/types.py
formed/integrations/ml/workflow.py
formed-0.0.5.dist-info/WHEEL
formed-0.0.5.dist-info/entry_points.txt
formed-0.0.5.dist-info/METADATA
formed-0.0.5.dist-info/RECORD
