Metadata-Version: 2.4
Name: formed
Version: 0.0.5
Summary: 🧬 Flexible framework for organizing data/experiments/workflows
Keywords: python,workflow
Author: altescy
Author-email: altescy <me@altescy.jp>
License-Expression: MIT
Classifier: License :: OSI Approved :: MIT License
Classifier: Programming Language :: Python :: 3
Classifier: Programming Language :: Python :: 3.11
Classifier: Programming Language :: Python :: 3.12
Classifier: Programming Language :: Python :: 3.13
Classifier: Programming Language :: Python :: 3.14
Requires-Dist: cloudpickle>=3.1.1
Requires-Dist: colt>=0.18.1
Requires-Dist: filelock
Requires-Dist: minato>=0.12
Requires-Dist: pyyaml
Requires-Dist: rich>=12.3
Requires-Dist: rjsonnet
Requires-Dist: typing-extensions>=4.15.0
Requires-Dist: datasets>=2.0 ; extra == 'all'
Requires-Dist: flax>=0.10 ; extra == 'all'
Requires-Dist: mlflow>=2.0 ; extra == 'all'
Requires-Dist: numpy>=1.26.4 ; extra == 'all'
Requires-Dist: protobuf>=5.0 ; extra == 'all'
Requires-Dist: scipy>=1.14 ; python_full_version >= '3.12' and extra == 'all'
Requires-Dist: scipy>=1.13 ; python_full_version < '3.12' and extra == 'all'
Requires-Dist: torch>=2.0 ; extra == 'all'
Requires-Dist: pyarrow>=18.0 ; python_full_version >= '3.12' and extra == 'all'
Requires-Dist: pyarrow ; python_full_version < '3.12' and extra == 'all'
Requires-Dist: sentence-transformers>=3.0 ; extra == 'all'
Requires-Dist: transformers[torch]>=4.0 ; extra == 'all'
Requires-Dist: flax>=0.10 ; extra == 'flax'
Requires-Dist: mlflow>=2.0 ; extra == 'mlflow'
Requires-Dist: mlflow>=3.6.0 ; python_full_version >= '3.14' and extra == 'mlflow'
Requires-Dist: numpy>=1.26.4 ; extra == 'mlflow'
Requires-Dist: scipy>=1.14 ; python_full_version >= '3.12' and extra == 'mlflow'
Requires-Dist: scipy>=1.13 ; python_full_version < '3.12' and extra == 'mlflow'
Requires-Dist: pyarrow>=22.0 ; python_full_version >= '3.14' and extra == 'mlflow'
Requires-Dist: pyarrow>=18.0 ; python_full_version >= '3.12' and extra == 'mlflow'
Requires-Dist: pyarrow ; python_full_version < '3.12' and extra == 'mlflow'
Requires-Dist: plotly>=6.3.0 ; extra == 'mlflow'
Requires-Dist: datasets>=2.0 ; extra == 'sentence-transformers'
Requires-Dist: sentence-transformers>=3.0 ; extra == 'sentence-transformers'
Requires-Dist: transformers[torch]>=4.0 ; extra == 'sentence-transformers'
Requires-Dist: torch>=2.0 ; extra == 'torch'
Requires-Dist: datasets>=2.0 ; extra == 'transformers'
Requires-Dist: protobuf>=5.0 ; extra == 'transformers'
Requires-Dist: transformers>=4.0 ; extra == 'transformers'
Requires-Python: >=3.11, <4.0
Project-URL: Homepage, https://altescy.jp/formed
Provides-Extra: all
Provides-Extra: flax
Provides-Extra: mlflow
Provides-Extra: sentence-transformers
Provides-Extra: torch
Provides-Extra: transformers
